nekuda/__init__.py
nekuda/_globals.py
nekuda/client.py
nekuda/exceptions.py
nekuda/models.py
nekuda/payment.py
nekuda/py.typed
nekuda/response_models.py
nekuda/user.py
nekuda/utils/__init__.py
nekuda/utils/http.py
nekuda/utils/validation.py
nekuda-0.2.9.dist-info/METADATA
nekuda-0.2.9.dist-info/WHEEL
nekuda-0.2.9.dist-info/licenses/LICENSE
nekuda-0.2.9.dist-info/RECORD
