Metadata-Version: 2.4
Name: nekuda
Version: 0.2.9
Summary: Python SDK for Nekuda payment processing
Project-URL: Homepage, https://nekuda.ai
Project-URL: Documentation, https://docs.nekuda.ai
Author-email: Nekuda AI <support@nekuda.ai>
License-Expression: Apache-2.0
License-File: LICENSE
Keywords: ai-agents,credit-card,fintech,nekuda,payments,sdk
Classifier: Development Status :: 3 - Alpha
Classifier: Intended Audience :: Developers
Classifier: License :: OSI Approved :: Apache Software License
Classifier: Operating System :: OS Independent
Classifier: Programming Language :: Python :: 3
Classifier: Programming Language :: Python :: 3 :: Only
Classifier: Programming Language :: Python :: 3.9
Classifier: Programming Language :: Python :: 3.10
Classifier: Programming Language :: Python :: 3.11
Classifier: Programming Language :: Python :: 3.12
Classifier: Topic :: Internet :: WWW/HTTP
Classifier: Topic :: Office/Business :: Financial
Classifier: Topic :: Software Development :: Libraries :: Python Modules
Classifier: Typing :: Typed
Requires-Python: >=3.9
Requires-Dist: httpx>=0.24.0
Requires-Dist: pydantic>=2.0.0
Requires-Dist: python-dotenv>=1.0.0
